django_mcp/__init__.py
django_mcp/py.typed
django_modelcontextprotocol-0.0.0.dist-info/METADATA
django_modelcontextprotocol-0.0.0.dist-info/WHEEL
django_modelcontextprotocol-0.0.0.dist-info/licenses/LICENSE
django_modelcontextprotocol-0.0.0.dist-info/RECORD
