Metadata-Version: 2.4
Name: django-modelcontextprotocol
Version: 0.0.0
Project-URL: Homepage, https://github.com/ppak10/django-modelcontextprotocol
Project-URL: Repository, https://github.com/ppak10/django-modelcontextprotocol
Author-email: Peter Pak <ppak10@gmail.com>
License-File: LICENSE
Requires-Python: >=3.10
